ipfs_node/__init__.py
ipfs_node/ipfs_files.py
ipfs_node/ipfs_node.py
ipfs_node/ipfs_peers.py
ipfs_node/ipfs_pubsub.py
ipfs_node/ipfs_tunnels.py
ipfs_node/utils/__init__.py
ipfs_node/utils/cid_utils.py
ipfs_node/utils/peer_utils.py
ipfs_node-0.1.11.dist-info/licenses/LICENSE
ipfs_node-0.1.11.dist-info/licenses/LICENSE-CC0
libkubo/__init__.py
libkubo/libkubo_android_arm64.h
libkubo/libkubo_linux_arm64.h
libkubo/libkubo_linux_arm64.so
libkubo/libkubo_linux_x86_64.h
libkubo/libkubo_linux_x86_64.so
libkubo/libkubo_loader.py
libkubo/libkubo_windows_x86_64.dll
libkubo/libkubo_windows_x86_64.h
ipfs_node-0.1.11.dist-info/METADATA
ipfs_node-0.1.11.dist-info/WHEEL
ipfs_node-0.1.11.dist-info/top_level.txt
ipfs_node-0.1.11.dist-info/RECORD
