Metadata-Version: 2.4
Name: ipfs_node
Version: 0.1.11
Summary: Run an IPFS node inside of python using kubo as a library.
Home-page: https://github.com/emendir/py_ipfs_node
Author: Emendir
Author-email: 
Classifier: Programming Language :: Python :: 3
Classifier: Operating System :: OS Independent
Requires-Python: >=3.7
License-File: LICENSE
License-File: LICENSE-CC0
Requires-Dist: cffi>=1.15.0
Requires-Dist: ipfs_tk
Dynamic: author
Dynamic: classifier
Dynamic: description
Dynamic: description-content-type
Dynamic: home-page
Dynamic: license-file
Dynamic: requires-dist
Dynamic: requires-python
Dynamic: summary
